{
  "updated_at": "2025-11-20 08:17:01",
  "total_trades": 12,
  "trades": [
    {
      "politician": "David Taylor",
      "party": "Republican",
      "chamber": "House",
      "state": "OH",
      "traded_issuer": "Alphabet Inc",
      "ticker": "GOOGL",
      "sector": "N/A",
      "published": "14:05Yesterday",
      "traded": "3 Nov2025",
      "filed_after": "15 days",
      "owner": "Undisclosed",
      "type": "Sell",
      "size": "1K–15K",
      "value": 8000,
      "price": "$283.72"
    },
    {
      "politician": "David Taylor",
      "party": "Republican",
      "chamber": "House",
      "state": "OH",
      "traded_issuer": "Alphabet Inc",
      "ticker": "GOOGL",
      "sector": "N/A",
      "published": "14:05Yesterday",
      "traded": "3 Nov2025",
      "filed_after": "15 days",
      "owner": "Undisclosed",
      "type": "Sell",
      "size": "1K–15K",
      "value": 8000,
      "price": "$283.72"
    },
    {
      "politician": "David Taylor",
      "party": "Republican",
      "chamber": "House",
      "state": "OH",
      "traded_issuer": "American Electric Power Co Inc",
      "ticker": "AEP",
      "sector": "N/A",
      "published": "14:05Yesterday",
      "traded": "3 Nov2025",
      "filed_after": "15 days",
      "owner": "Undisclosed",
      "type": "Sell",
      "size": "1K–15K",
      "value": 8000,
      "price": "$119.92"
    },
    {
      "politician": "David Taylor",
      "party": "Republican",
      "chamber": "House",
      "state": "OH",
      "traded_issuer": "American Electric Power Co Inc",
      "ticker": "AEP",
      "sector": "N/A",
      "published": "14:05Yesterday",
      "traded": "3 Nov2025",
      "filed_after": "15 days",
      "owner": "Undisclosed",
      "type": "Sell",
      "size": "1K–15K",
      "value": 8000,
      "price": "$119.92"
    },
    {
      "politician": "David Taylor",
      "party": "Republican",
      "chamber": "House",
      "state": "OH",
      "traded_issuer": "The Home Depot Inc",
      "ticker": "HD",
      "sector": "N/A",
      "published": "14:05Yesterday",
      "traded": "11 Nov2025",
      "filed_after": "7 days",
      "owner": "Undisclosed",
      "type": "Buy",
      "size": "1K–15K",
      "value": 8000,
      "price": "$374.24"
    },
    {
      "politician": "David Taylor",
      "party": "Republican",
      "chamber": "House",
      "state": "OH",
      "traded_issuer": "Installed Building Products Inc",
      "ticker": "IBP",
      "sector": "N/A",
      "published": "14:05Yesterday",
      "traded": "3 Nov2025",
      "filed_after": "15 days",
      "owner": "Undisclosed",
      "type": "Buy",
      "size": "1K–15K",
      "value": 8000,
      "price": "$240.09"
    },
    {
      "politician": "David Taylor",
      "party": "Republican",
      "chamber": "House",
      "state": "OH",
      "traded_issuer": "Installed Building Products Inc",
      "ticker": "IBP",
      "sector": "N/A",
      "published": "14:05Yesterday",
      "traded": "3 Nov2025",
      "filed_after": "15 days",
      "owner": "Undisclosed",
      "type": "Buy",
      "size": "1K–15K",
      "value": 8000,
      "price": "$240.09"
    },
    {
      "politician": "David Taylor",
      "party": "Republican",
      "chamber": "House",
      "state": "OH",
      "traded_issuer": "The Progressive Corp",
      "ticker": "PGR",
      "sector": "N/A",
      "published": "14:05Yesterday",
      "traded": "3 Nov2025",
      "filed_after": "15 days",
      "owner": "Undisclosed",
      "type": "Buy",
      "size": "1K–15K",
      "value": 8000,
      "price": "$203.70"
    },
    {
      "politician": "David Taylor",
      "party": "Republican",
      "chamber": "House",
      "state": "OH",
      "traded_issuer": "The Progressive Corp",
      "ticker": "PGR",
      "sector": "N/A",
      "published": "14:05Yesterday",
      "traded": "3 Nov2025",
      "filed_after": "15 days",
      "owner": "Undisclosed",
      "type": "Buy",
      "size": "1K–15K",
      "value": 8000,
      "price": "$203.70"
    },
    {
      "politician": "David Taylor",
      "party": "Republican",
      "chamber": "House",
      "state": "OH",
      "traded_issuer": "RPM International Inc",
      "ticker": "RPM",
      "sector": "N/A",
      "published": "14:05Yesterday",
      "traded": "11 Nov2025",
      "filed_after": "7 days",
      "owner": "Undisclosed",
      "type": "Buy",
      "size": "1K–15K",
      "value": 8000,
      "price": "$107.46"
    },
    {
      "politician": "David Taylor",
      "party": "Republican",
      "chamber": "House",
      "state": "OH",
      "traded_issuer": "Visa Inc",
      "ticker": "V",
      "sector": "N/A",
      "published": "14:05Yesterday",
      "traded": "12 Nov2025",
      "filed_after": "6 days",
      "owner": "Undisclosed",
      "type": "Buy",
      "size": "1K–15K",
      "value": 8000,
      "price": "$338.88"
    },
    {
      "politician": "Byron Donalds",
      "party": "Republican",
      "chamber": "House",
      "state": "FL",
      "traded_issuer": "Brown & Brown Inc",
      "ticker": "BRO",
      "sector": "N/A",
      "published": "14:05Yesterday",
      "traded": "9 Oct2025",
      "filed_after": "40 days",
      "owner": "Undisclosed",
      "type": "Buy",
      "size": "1K–15K",
      "value": 8000,
      "price": "$95.50"
    }
  ]
}